{
  "transactions": [
    {
      "id": "1",
      "name": "Acme Corp Payroll",
      "type": "income",
      "category": "Salary",
      "amount": 3200,
      "date": "2025-09-01"
    },
    {
      "id": "2",
      "name": "Shell Gas Station",
      "type": "expense",
      "category": "Transport",
      "amount": 45,
      "date": "2025-09-03"
    },
    {
      "id": "3",
      "name": "Netflix Subscription",
      "type": "expense",
      "category": "Entertainment",
      "amount": 15,
      "date": "2025-09-04"
    },
    {
      "id": "4",
      "name": "Acme Corp Payroll",
      "type": "income",
      "category": "Salary",
      "amount": 3200,
      "date": "2025-10-01"
    },
    {
      "id": "5",
      "name": "Walmart Supercenter",
      "type": "expense",
      "category": "Groceries",
      "amount": 95,
      "date": "2025-10-03"
    },
    {
      "id": "6",
      "name": "Uber Ride",
      "type": "expense",
      "category": "Transport",
      "amount": 22,
      "date": "2025-10-05"
    },
    {
      "id": "7",
      "name": "Spotify Premium",
      "type": "expense",
      "category": "Entertainment",
      "amount": 10,
      "date": "2025-10-06"
    },
    {
      "id": "8",
      "name": "Trader Joe’s",
      "type": "expense",
      "category": "Groceries",
      "amount": 120,
      "date": "2025-10-07"
    },
    {
      "id": "9",
      "name": "Lyft Ride",
      "type": "expense",
      "category": "Transport",
      "amount": 38,
      "date": "2025-10-08"
    },
    {
      "id": "10",
      "name": "Toyota Service Center",
      "type": "expense",
      "category": "Transport",
      "amount": 343,
      "date": "2023-02-13"
    }
  ],
  "categories": [
    {
      "id": "1",
      "name": "Salary",
      "type": "income"
    },
    {
      "id": "2",
      "name": "Groceries",
      "type": "expense"
    },
    {
      "id": "3",
      "name": "Transport",
      "type": "expense"
    },
    {
      "id": "4",
      "name": "Entertainment",
      "type": "expense"
    }
  ]
}
